gitgraphz/__init__.py
gitgraphz/gitgraphz.py
gitgraphz-1.1.0.dist-info/licenses/LICENSE
gitgraphz-1.1.0.dist-info/METADATA
gitgraphz-1.1.0.dist-info/WHEEL
gitgraphz-1.1.0.dist-info/entry_points.txt
gitgraphz-1.1.0.dist-info/top_level.txt
gitgraphz-1.1.0.dist-info/RECORD
