Metadata-Version: 2.4
Name: gitgraphz
Version: 1.1.0
Summary: A git graph tool
Author-email: Stephan Bechter <stephan@apogeum.at>
License: GPL-2.0-only
Classifier: License :: OSI Approved :: GNU General Public License v2 (GPLv2)
Classifier: Programming Language :: Python :: 3
Classifier: Operating System :: POSIX :: Linux
Classifier: Operating System :: POSIX :: Linux
Requires-Python: >=3.10
License-File: LICENSE
Dynamic: license-file
